{"id":"2019-11-07-laravel-poznan-meetup-13","name":"Laravel Poznań Meetup #13","location":"Poznań, Plus Jeden","date":"2019-11-07 18:00:00","dateFull":"7 listopada 2019, 18:00","presentations":[{"title":"AOP w Laravel","youtube":null,"slideshare":null,"speakers":[{"id":"1","name":"Mateusz Antkowiak","image":"","slug":"1-mateusz-antkowiak","avatar":"https://ui-avatars.com/api/?background=random&font-size=.33&size-128&rounded=true&name=Mateusz-Antkowiak","linkedin":"https://www.linkedin.com/in/mateusz-antkowiak-696357109/","company":{"name":"Transparent Data","slug":"8-transparent-data"}}],"tags":[]},{"title":"Dobre praktyki w Laravel - live coding","youtube":null,"slideshare":null,"speakers":[{"id":"15","name":"Piotr Nowak","image":"/images/speakers/piotrnowak.webp","slug":"15-piotr-nowak","avatar":"https://ui-avatars.com/api/?background=random&font-size=.33&size-128&rounded=true&name=Piotr-Nowak","linkedin":"https://www.linkedin.com/in/nowakjestem/","company":{"name":"HighSolutions","slug":"7-highsolutions"}}],"tags":[]}],"facebook":"https://www.facebook.com/events/291362435056567/355357788657031"}